conformalpy/__init__.py
conformalpy/classifier/__init__.py
conformalpy/classifier/conformal_classifier.py
conformalpy/evaluation/__init__.py
conformalpy/evaluation/classification_metrics.py
conformalpy/nonconformity/__init__.py
conformalpy/nonconformity/classification.py
conformalpy/plots/__init__.py
conformalpy/plots/classification.py
conformalpy-0.0.1.dist-info/licenses/LICENSE
conformalpy-0.0.1.dist-info/METADATA
conformalpy-0.0.1.dist-info/WHEEL
conformalpy-0.0.1.dist-info/top_level.txt
conformalpy-0.0.1.dist-info/RECORD
